celoMine/PredictivePR.py
celoMine/__init__.py
celoMine-0.0.7.dist-info/LICENSE
celoMine-0.0.7.dist-info/METADATA
celoMine-0.0.7.dist-info/WHEEL
celoMine-0.0.7.dist-info/top_level.txt
celoMine-0.0.7.dist-info/RECORD
