Metadata-Version: 2.1
Name: celoMine
Version: 0.0.7
Summary: Predictive machine learning for Celonis
Home-page: https://github.com/JeanBertinR/celoMine
Author: Jean BERTIN
Author-email: <jeanbertin.ensam@gmail.com>
License: GPL-v3
Keywords: celonis,process mining,machine learning
Classifier: Development Status :: 1 - Planning
Classifier: Intended Audience :: Developers
Classifier: Programming Language :: Python :: 3
Classifier: Operating System :: Unix
Classifier: Operating System :: MacOS :: MacOS X
Classifier: Operating System :: Microsoft :: Windows
License-File: LICENSE
Requires-Dist: pandas
Requires-Dist: numpy
Requires-Dist: scikit-learn
Requires-Dist: matplotlib
